repocards/__init__.py
repocards/__main__.py
repocards/api.py
repocards/cli.py
repocards/schemas.py
repocards/analyzers/imaging.py
repocards/core/__init__.py
repocards/core/detectors.py
repocards/core/extractors.py
repocards/core/fetcher.py
repocards/core/summarizer.py
repocards-0.1.3.dist-info/licenses/LICENSE
repocards-0.1.3.dist-info/METADATA
repocards-0.1.3.dist-info/WHEEL
repocards-0.1.3.dist-info/entry_points.txt
repocards-0.1.3.dist-info/top_level.txt
repocards-0.1.3.dist-info/RECORD
