Metadata-Version: 2.4
Name: repocards
Version: 0.1.3
Summary: Evidence-based repository summarizer that generates comprehensive documentation cards from any GitHub or GitLab project.
Author-email: Quentin Chappuis <quentin.chappuis@epfl.ch>
License: MIT
Project-URL: Homepage, https://github.com/qchapp/repocards
Project-URL: Repository, https://github.com/qchapp/repocards
Project-URL: Issues, https://github.com/qchapp/repocards/issues
Keywords: github,documentation,analysis,repository,automation
Classifier: Development Status :: 4 - Beta
Classifier: Intended Audience :: Developers
Classifier: License :: OSI Approved :: MIT License
Classifier: Programming Language :: Python :: 3
Classifier: Programming Language :: Python :: 3.9
Classifier: Programming Language :: Python :: 3.10
Classifier: Programming Language :: Python :: 3.11
Classifier: Programming Language :: Python :: 3.12
Classifier: Topic :: Software Development :: Documentation
Classifier: Topic :: Software Development :: Libraries :: Python Modules
Requires-Python: >=3.9
License-File: LICENSE
Requires-Dist: requests>=2.31
Requires-Dist: pydantic>=2.0
Requires-Dist: pyyaml>=6.0
Requires-Dist: typer>=0.12
Requires-Dist: python-dotenv
Provides-Extra: dev
Requires-Dist: pytest>=8.0; extra == "dev"
Requires-Dist: pytest-cov>=4.0; extra == "dev"
Dynamic: license-file
